Controlador.v
module Controlador (
    input clk,
    input reset,
    input insere,
    input [3:0] numero, 
    output reg [3:0] estado,
    output reg [6:0] display,
    output reg led
);

    // Definir os estados com parâmetros
    localparam inicial = 4'b0000;
    localparam certo1_erro0 = 4'b0001;
    localparam certo2_erro0 = 4'b0010;
    localparam certo3_erro0 = 4'b0011;
    localparam certo4_erro0 = 4'b0100;
    localparam certo5_erro0 = 4'b0101;
    localparam sucessototal = 4'b0110;
    localparam certo0_erro1 = 4'b0111;
    localparam certo1_erro1 = 4'b1000;
    localparam certo2_erro1 = 4'b1001;
    localparam certo3_erro1 = 4'b1010;
    localparam certo4_erro1 = 4'b1011;
    localparam certo5_erro1 = 4'b1100;
    localparam sucessoparcial = 4'b1110;
    localparam falha = 4'b1111;

    // Registro para estado atual e próximo
    reg [3:0] estadoatual, proximoestado;

    // Lógica de transição de estados
    always @(posedge clk or posedge reset) begin
        if (reset) begin
            estadoatual <= inicial;
        end else begin
            estadoatual <= proximoestado;
        end
    end

    

    // Lógica de próximo estado
    always @(*) begin

        

        if (insere) begin
            case (estadoatual)
                inicial: begin
                    led = 0; // Valor padrão
                    if ((numero != 4'b0101) && (numero <= 9)) begin
                        proximoestado = certo0_erro1;
                        led = 1;
                    end else if (numero == 4'b0101) begin
                        proximoestado = certo1_erro0;
                        led = 0;
                    end else begin
                        proximoestado = inicial;
                    end
                end
                certo1_erro0: begin
                    if ((numero != 4'b1000) && (numero <= 9)) begin
                        proximoestado = certo1_erro1;
                        led = 1;
                    end else if (numero == 4'b1000) begin
                        proximoestado = certo2_erro0;
                        led = 0;
                    end else begin
                        proximoestado = certo1_erro0;
                    end
                end
                certo2_erro0: begin
                    if ((numero != 4'b1001) && (numero <= 9)) begin
                        proximoestado = certo2_erro1;
                        led = 1;
                    end else if (numero == 4'b1001) begin
                        proximoestado = certo3_erro0;
                        led = 0;
                    end else begin
                        proximoestado = certo2_erro0;
                    end
                end
                certo3_erro0: begin
                    if ((numero != 4'b0010) && (numero <= 9)) begin
                        proximoestado = certo3_erro1;
                        led = 1;
                    end else if (numero == 4'b0010) begin
                        proximoestado = certo4_erro0;
                        led = 0;
                    end else begin
                        proximoestado = certo3_erro0;
                    end
                end
                certo4_erro0: begin
                    if ((numero != 4'b0000) && (numero <= 9)) begin
                        proximoestado = certo4_erro1;
                        led = 1;
                    end else if (numero == 4'b0000) begin
                        proximoestado = certo5_erro0;
                        led = 0;
                    end else begin
                        proximoestado = certo4_erro0;
                    end
                end
                certo5_erro0: begin
                    if ((numero != 4'b0100) && (numero <= 9)) begin
                        proximoestado = certo5_erro1;
                        led = 1;
                    end else if (numero == 4'b0100) begin
                        proximoestado = sucessototal;
                        led = 0;
                    end else begin
                        proximoestado = certo5_erro0;
                    end
                end
                sucessototal: begin
                    proximoestado = sucessototal;
                end
                certo0_erro1: begin
                    if((numero != 4'b0101) && (numero <= 9)) begin
                        proximoestado = falha;
                    end else if (numero == 4'b0101) begin
                        proximoestado = certo1_erro1;
                    end else begin
                        proximoestado = certo0_erro1;
                    end
                end
                certo1_erro1: begin
                    if((numero != 4'b1000) && (numero <= 9)) begin
                        proximoestado = falha;
                    end else if (numero == 4'b1000) begin
                        proximoestado = certo2_erro1;
                    end else begin
                        proximoestado = certo1_erro1;
                    end
                end
                certo2_erro1: begin
                    if((numero != 4'b0110) && (numero <= 9)) begin
                        proximoestado = falha;
                    end else if (numero == 4'b0110) begin
                        proximoestado = certo3_erro1;
                    end else begin
                        proximoestado = certo2_erro1;
                    end
                end
                certo3_erro1: begin
                    if((numero != 4'b0010) && (numero <= 9)) begin
                        proximoestado = falha;
                    end else if (numero == 4'b0010) begin
                        proximoestado = certo4_erro1;
                    end else begin
                        proximoestado = certo3_erro1;
                    end
                end
                certo4_erro1: begin
                    if((numero != 4'b0000) && (numero <= 9)) begin
                        proximoestado = falha;
                    end else if (numero == 4'b0000) begin
                        proximoestado = certo5_erro1;
                    end else begin
                        proximoestado = certo4_erro1;
                    end
                end
                certo5_erro1: begin
                    if((numero != 4'b0100) && (numero <= 9)) begin
                        proximoestado = falha;
                    end else if (numero == 4'b0100) begin
                        proximoestado = sucessoparcial;
                    end else begin
                        proximoestado = certo5_erro1;
                    end
                end
                sucessoparcial: begin
                    proximoestado = sucessoparcial;
                end
                falha: begin
                    proximoestado = falha;
                end
                default: proximoestado = inicial;
            endcase
        end else begin
            proximoestado = estadoatual; // Quando `insere` não é ativo, o estado não muda
        end
    end

    // Lógica de saída
    always @(*) begin
        estado = estadoatual;
        case (estado)
            inicial: display = 7'b0000001;
            sucessototal: display = 7'b0100100;
            sucessoparcial: display = 7'b0011000;
            falha: display = 7'b0111000;
            default: begin
                case (numero)
                    4'b0000: display = 7'b0000001;
                    4'b0001: display = 7'b1001111;
                    4'b0010: display = 7'b0010010;
                    4'b0011: display = 7'b0000110;
                    4'b0100: display = 7'b1001100;
                    4'b0101: display = 7'b0100100;
                    4'b0110: display = 7'b0100000;
                    4'b0111: display = 7'b0001111;
                    4'b1000: display = 7'b0000000;
                    4'b1001: display = 7'b0000010;
                    default: display = 7'b1111110;
                endcase
            end
        endcase
    end

    // Debug (simulação)
always @(posedge clk) begin
    $display("Numero inserido: %d, led: %d", numero, led);
    if (reset) begin
        $display("Reset: estado = %b", estadoatual);
    end else begin
        $display("Estado Atual: %b, Proximo Estado: %b", estadoatual, proximoestado);
    end
end

endmodule

Controlador_tb.v
`timescale 1ns / 1ps

module Controlador_tb;

    // Declaração de variáveis de entrada e saída
    reg clk;
    reg reset;
    reg insere;
    reg [3:0] numero;
    wire [3:0] estado;
    wire [6:0] display;
    wire led;

    // Instância do módulo Controlador
    Controlador dut (
        .clk(clk),
        .reset(reset),
        .insere(insere),
        .numero(numero),
        .estado(estado),
        .display(display),
        .led(led)
    );

    // Geração do clock
    initial begin
        clk = 0; // Inicializa o clock com 0
        forever #5 clk = ~clk; // Alterna o clock a cada 5 unidades de tempo (período total = 10ns)
    end

    // Geração do arquivo de onda e sequência de testes
    initial begin
        $dumpfile("Controlador_tb.vcd");
        $dumpvars(0, Controlador_tb);

        // Inicialização
        reset = 1;
        insere = 0;
        //numero = 4'b0000;
        #10; // Aguarda 20ns com reset ativo

        // Libera o reset e ativa a entrada
        reset = 0;
        insere = 1;

        // Teste 1: Insere sequência com números corretos e incorretos
        numero = 4'b0101; // Número correto: 5
        #10;
        numero = 4'b0111; // Número incorreto: 7
        #10;
        numero = 4'b1000; // Número correto: 8
        #10;
        numero = 4'b1010; // Número inválido: 10 (>9)
        #10;
        numero = 4'b0000; // Número incorreto: 0
        #10;

        // Teste 2: Resetar e iniciar novamente
        reset = 1;
        #10;
        reset = 0;

        // Teste 3: Sequência completa para sucesso total
        numero = 4'b0101; // Número correto: 5
        #10;
        numero = 4'b1000; // Número correto: 8
        #10;
        numero = 4'b1001; // Número correto: 9
        #10;
        numero = 4'b0010; // Número correto: 2
        #10;
        numero = 4'b0000; // Número correto: 0
        #10;
        numero = 4'b0100; // Número correto: 4
        #10;

        // Teste 4: Reset no meio da sequência
        reset = 1;
        #10;
        reset = 0;

        //Sequência para sucesso parcial
        numero = 4'b0101; // Número correto: 5
        #10;
        numero = 4'b1000; // Número correto: 8
        #10;
        numero = 4'b1001; // Número correto: 9
        #10;
        numero = 4'b0010; // Número correto: 2
        #10;
        numero = 4'b0001; // Número incorreto: 1
        #10;
        numero = 4'b0000; // Número correto: 0
        #10;
        numero = 4'b0100; // Número correto: 4
        #10;

        // Finaliza a simulação
        $finish;
    end

endmodule

Controlador_tb.vcd
$date
	Tue Jan 14 15:50:47 2025
$end
$version
	Icarus Verilog
$end
$timescale
	1ps
$end
$scope module Controlador_tb $end
$var wire 1 ! led $end
$var wire 4 " estado [3:0] $end
$var wire 7 # display [6:0] $end
$var reg 1 $ clk $end
$var reg 1 % insere $end
$var reg 4 & numero [3:0] $end
$var reg 1 ' reset $end
$scope module dut $end
$var wire 1 $ clk $end
$var wire 1 % insere $end
$var wire 4 ( numero [3:0] $end
$var wire 1 ' reset $end
$var parameter 4 ) certo0_erro1 $end
$var parameter 4 * certo1_erro0 $end
$var parameter 4 + certo1_erro1 $end
$var parameter 4 , certo2_erro0 $end
$var parameter 4 - certo2_erro1 $end
$var parameter 4 . certo3_erro0 $end
$var parameter 4 / certo3_erro1 $end
$var parameter 4 0 certo4_erro0 $end
$var parameter 4 1 certo4_erro1 $end
$var parameter 4 2 certo5_erro0 $end
$var parameter 4 3 certo5_erro1 $end
$var parameter 4 4 falha $end
$var parameter 4 5 inicial $end
$var parameter 4 6 sucessoparcial $end
$var parameter 4 7 sucessototal $end
$var reg 7 8 display [6:0] $end
$var reg 4 9 estado [3:0] $end
$var reg 4 : estadoatual [3:0] $end
$var reg 1 ! led $end
$var reg 4 ; proximoestado [3:0] $end
$upscope $end
$upscope $end
$enddefinitions $end
$comment Show the parameter values. $end
$dumpall
b110 7
b1110 6
b0 5
b1111 4
b1100 3
b101 2
b1011 1
b100 0
b1010 /
b11 .
b1001 -
b10 ,
b1000 +
b1 *
b111 )
$end
#0
$dumpvars
b0 ;
b0 :
b0 9
b1 8
bx (
1'
bx &
0%
0$
b1 #
b0 "
x!
$end
#5000
1$
#10000
b1 ;
0!
0$
b101 &
b101 (
1%
0'
#15000
b100100 #
b100100 8
b1 "
b1 9
1!
b1000 ;
b1 :
1$
#20000
b1111 #
b1111 8
0$
b111 &
b111 (
#25000
b1000 "
b1000 9
b1111 ;
b1000 :
1$
#30000
b0 #
b0 8
b1001 ;
0$
b1000 &
b1000 (
#35000
b1001 "
b1001 9
b1111 ;
b1001 :
1$
#40000
b1111110 #
b1111110 8
b1001 ;
0$
b1010 &
b1010 (
#45000
1$
#50000
b1 #
b1 8
b1111 ;
0$
b0 &
b0 (
#55000
b111000 #
b111000 8
b1111 "
b1111 9
b1111 :
1$
#60000
b1 #
b1 8
b0 "
b0 9
b111 ;
1!
b0 :
0$
1'
#65000
1$
#70000
b1 ;
0!
0$
b101 &
b101 (
0'
#75000
b100100 #
b100100 8
b1 "
b1 9
1!
b1000 ;
b1 :
1$
#80000
b0 #
b0 8
0!
b10 ;
0$
b1000 &
b1000 (
#85000
b10 "
b10 9
1!
b1001 ;
b10 :
1$
#90000
b10 #
b10 8
0!
b11 ;
0$
b1001 &
b1001 (
#95000
b11 "
b11 9
1!
b1010 ;
b11 :
1$
#100000
b10010 #
b10010 8
0!
b100 ;
0$
b10 &
b10 (
#105000
b100 "
b100 9
1!
b1011 ;
b100 :
1$
#110000
b1 #
b1 8
0!
b101 ;
0$
b0 &
b0 (
#115000
b101 "
b101 9
1!
b1100 ;
b101 :
1$
#120000
b1001100 #
b1001100 8
0!
b110 ;
0$
b100 &
b100 (
#125000
b100100 #
b100100 8
b110 "
b110 9
b110 :
1$
#130000
b1 #
b1 8
b0 "
b0 9
1!
b111 ;
b0 :
0$
1'
#135000
1$
#140000
b1 ;
0!
0$
b101 &
b101 (
0'
#145000
b100100 #
b100100 8
b1 "
b1 9
1!
b1000 ;
b1 :
1$
#150000
b0 #
b0 8
0!
b10 ;
0$
b1000 &
b1000 (
#155000
b10 "
b10 9
1!
b1001 ;
b10 :
1$
#160000
b10 #
b10 8
0!
b11 ;
0$
b1001 &
b1001 (
#165000
b11 "
b11 9
1!
b1010 ;
b11 :
1$
#170000
b10010 #
b10010 8
0!
b100 ;
0$
b10 &
b10 (
#175000
b100 "
b100 9
1!
b1011 ;
b100 :
1$
#180000
b1001111 #
b1001111 8
0$
b1 &
b1 (
#185000
b1011 "
b1011 9
b1111 ;
b1011 :
1$
#190000
b1 #
b1 8
b1100 ;
0$
b0 &
b0 (
#195000
b1100 "
b1100 9
b1111 ;
b1100 :
1$
#200000
b1001100 #
b1001100 8
b1110 ;
0$
b100 &
b100 (
#205000
b11000 #
b11000 8
b1110 "
b1110 9
b1110 :
1$
